tap_sec/__init__.py
tap_sec/client.py
tap_sec/core_scraper/__init__.py
tap_sec/core_scraper/scraper.py
tap_sec/streams.py
tap_sec/tap.py
tap_sec/tests/__init__.py
tap_sec/tests/test_core.py
tap_sec-0.0.1.dist-info/entry_points.txt
tap_sec-0.0.1.dist-info/WHEEL
tap_sec-0.0.1.dist-info/METADATA
tap_sec-0.0.1.dist-info/RECORD
